jncep/__init__.py
jncep/config.py
jncep/core.py
jncep/epub.py
jncep/jncalts.py
jncep/jncapi.py
jncep/jncep.py
jncep/jncweb.py
jncep/model.py
jncep/namegen.py
jncep/namegen_minilang.py
jncep/namegen_utils.py
jncep/spec.py
jncep/track.py
jncep/trio_utils.py
jncep/update.py
jncep/utils.py
jncep/cli/__init__.py
jncep/cli/base.py
jncep/cli/config.py
jncep/cli/epub.py
jncep/cli/options.py
jncep/cli/track.py
jncep/cli/update.py
jncep/res/en_stopwords.txt
jncep/res/style.css
jncep-55.dist-info/METADATA
jncep-55.dist-info/WHEEL
jncep-55.dist-info/entry_points.txt
jncep-55.dist-info/licenses/LICENSE
jncep-55.dist-info/RECORD
