Metadata-Version: 2.4
Name: jncep
Version: 55
Summary: Command-line tool to generate EPUB files for J-Novel Club and JNC Nina pre-pub novels
Project-URL: Homepage, https://github.com/gvellut/jncep
Project-URL: Repository, https://github.com/gvellut/jncep
Project-URL: Issues, https://github.com/gvellut/jncep/issues
Project-URL: Releases, https://github.com/gvellut/jncep/releases
Author-email: Guilhem Vellut <guilhem.vellut@gmail.com>
License-Expression: GPL-3.0-or-later
License-File: LICENSE
Keywords: epub,jnc,jnovel
Classifier: Development Status :: 5 - Production/Stable
Classifier: Environment :: Console
Classifier: Intended Audience :: Other Audience
Classifier: License :: OSI Approved :: GNU General Public License v3 or later (GPLv3+)
Classifier: Natural Language :: English
Classifier: Operating System :: OS Independent
Classifier: Programming Language :: Python :: 3
Classifier: Topic :: Utilities
Requires-Python: >=3.9
Requires-Dist: addict==2.4.0
Requires-Dist: atomicwrites==1.4.1
Requires-Dist: attrs==25.3.0
Requires-Dist: click-option-group==0.5.6
Requires-Dist: click==8.1.8
Requires-Dist: ebooklib==0.19
Requires-Dist: exceptiongroup==1.3.0
Requires-Dist: httpx==0.28.1
Requires-Dist: lark==1.2.2
Requires-Dist: outcome==1.3.0.post0
Requires-Dist: python-dateutil==2.9.0.post0
Requires-Dist: rich==13.9.4
Requires-Dist: trio==0.30.0
